LICENSE
labfunctions/__init__.py
labfunctions/__version__.py
labfunctions/alembic.ini
labfunctions/cli.py
labfunctions/client/__init__.py
labfunctions/client/base.py
labfunctions/client/cluster_client.py
labfunctions/client/diskclient.py
labfunctions/client/history_client.py
labfunctions/client/init_script.py
labfunctions/client/labstate.py
labfunctions/client/nbclient.py
labfunctions/client/projects_client.py
labfunctions/client/shortcuts.py
labfunctions/client/utils.py
labfunctions/client/workflows_client.py
labfunctions/cluster/__init__.py
labfunctions/cluster/base.py
labfunctions/cluster/control.py
labfunctions/cluster/deploy.py
labfunctions/cluster/providers/gcloud.py
labfunctions/cluster/providers/local.py
labfunctions/cluster/ssh.py
labfunctions/cluster/types.py
labfunctions/cmd/__init__.py
labfunctions/cmd/agent.py
labfunctions/cmd/cluster.py
labfunctions/cmd/common.py
labfunctions/cmd/executors.py
labfunctions/cmd/history.py
labfunctions/cmd/manager.py
labfunctions/cmd/project.py
labfunctions/cmd/runtimes.py
labfunctions/cmd/services.py
labfunctions/cmd/utils.py
labfunctions/cmd/workflows.py
labfunctions/commands.py
labfunctions/conf/__init__.py
labfunctions/conf/client_settings.py
labfunctions/conf/global_client.py
labfunctions/conf/global_settings.py
labfunctions/conf/jtemplates.py
labfunctions/conf/server_settings.py
labfunctions/conf/templates/Dockerfile.default
labfunctions/conf/templates/Dockerfile.generic
labfunctions/conf/templates/Dockerfile.internal
labfunctions/conf/templates/Makefile
labfunctions/conf/templates/__init__.py
labfunctions/conf/templates/agent.docker.envfile
labfunctions/conf/templates/client_settings.py.j2
labfunctions/conf/templates/docker-compose.yaml
labfunctions/conf/templates/dockerignore
labfunctions/conf/templates/gitignore
labfunctions/conf/templates/local.nbvars.j2
labfunctions/conf/templates/requirements_client.txt
labfunctions/conf/templates/runtimes.yaml
labfunctions/conf/templates/test_workflow.ipynb.j2
labfunctions-0.9.0.dist-info/entry_points.txt
labfunctions-0.9.0.dist-info/LICENSE
labfunctions-0.9.0.dist-info/WHEEL
labfunctions-0.9.0.dist-info/METADATA
labfunctions-0.9.0.dist-info/RECORD
