Metadata-Version: 2.1
Name: labfunctions
Version: 0.9.0
Summary: Schedule parameterized notebooks programmatically using cli or a REST API
Home-page: https://github.com/nuxion/labfunctions
License: Apache-2.0
Keywords: papermill,jupyter,workflows,data
Author: nuxion
Author-email: nuxion@gmail.com
Requires-Python: >=3.8,<3.11
Classifier: Environment :: Console
Classifier: Environment :: Web Environment
Classifier: Framework :: Jupyter :: JupyterLab
Classifier: License :: OSI Approved :: Apache Software License
Classifier: Operating System :: POSIX :: Linux
Classifier: Programming Language :: Python :: 3
Classifier: Programming Language :: Python :: 3.10
Classifier: Programming Language :: Python :: 3.8
Classifier: Programming Language :: Python :: 3.9
Classifier: Topic :: Scientific/Engineering :: Artificial Intelligence
Provides-Extra: cloud
Provides-Extra: server
Provides-Extra: stores
Requires-Dist: Jinja2 (>=3.0.3,<4.0.0)
Requires-Dist: PyJWT (>=2.1.0,<2.2.0)
Requires-Dist: PyYAML (>=6.0,<7.0)
Requires-Dist: SQLAlchemy-serializer (>=1.4.1,<2.0.0); extra == "server"
Requires-Dist: SQLAlchemy[asyncio] (>=1.4.26,<2.0.0); extra == "server"
Requires-Dist: aiofiles (>=0.8.0,<0.9.0)
Requires-Dist: aiosqlite (>=0.17.0,<0.18.0)
Requires-Dist: alembic (>=1.6.5,<2.0.0); extra == "server"
Requires-Dist: apache-libcloud (>=3.5.1,<4.0.0); extra == "cloud"
Requires-Dist: asyncpg (>=0.24.0,<0.25.0); extra == "server"
Requires-Dist: asyncssh (>=2.10.0,<3.0.0)
Requires-Dist: click (>=8.0.1,<9.0.0)
Requires-Dist: cloudpickle (>=2.0.0,<3.0.0)
Requires-Dist: cryptography (>=36.0.1,<37.0.0)
Requires-Dist: dateparser (>=1.1.0,<2.0.0)
Requires-Dist: docker (>=5.0.3,<6.0.0)
Requires-Dist: hiredis (>=2.0.0,<3.0.0)
Requires-Dist: httpx (<0.22.0)
Requires-Dist: ipykernel (>=6.9.1,<7.0.0)
Requires-Dist: jupytext (>=1.13.0,<2.0.0)
Requires-Dist: libq (>=0.7.4,<0.8.0)
Requires-Dist: loky (>=3.0.0,<4.0.0)
Requires-Dist: nanoid (>=2.0.0,<3.0.0)
Requires-Dist: nbconvert (>=6.2.0,<7.0.0)
Requires-Dist: papermill (>=2.3.4,<3.0.0)
Requires-Dist: psycopg2-binary (>=2.9.1,<3.0.0); extra == "server"
Requires-Dist: pydantic (>=1.9.0,<2.0.0)
Requires-Dist: pytz (>=2022.1,<2023.0)
Requires-Dist: redis (>=4.3.1,<5.0.0)
Requires-Dist: rich (>=12.0.0,<13.0.0)
Requires-Dist: sanic (>=21.6.2,<22.0.0); extra == "server"
Requires-Dist: sanic-ext (>=21.9.0,<22.0.0); extra == "server"
Requires-Dist: sanic-openapi (>=21.6.1,<22.0.0); extra == "server"
Requires-Dist: smart-open[gcs,s3] (>=6.0.0,<7.0.0); extra == "stores"
Requires-Dist: tenacity (>=8.0.1,<9.0.0)
Requires-Dist: tqdm (>=4.62.3,<5.0.0)
Requires-Dist: uvloop (>=0.16.0,<0.17.0); extra == "server"
Project-URL: Documentation, https://nb-workflows.readthedocs.io/
Project-URL: Repository, https://github.com/nuxion/labfunctions
